.gitignore
README.rst
setup.py
splunk_logger/__init__.py
splunk_logger/splunk_logger.py
splunk_logger/unittest_utils.py
splunk_logger/utils.py
splunk_logger.egg-info/PKG-INFO
splunk_logger.egg-info/SOURCES.txt
splunk_logger.egg-info/dependency_links.txt
splunk_logger.egg-info/requires.txt
splunk_logger.egg-info/top_level.txt
splunk_logger/tests/__init__.py
splunk_logger/tests/test_splunk_logger.py
splunk_logger/tests/test_utils.py