Metadata-Version: 1.1
Name: splunk-logger
Version: 0.2.0
Summary: Splunk logger sends log messages to splunk directly from your Python code.
Home-page: https://github.com/andresriancho/splunk-logger/
Author: Andres Riancho
Author-email: andres.riancho@gmail.com
License: GNU General Public License v2 (GPLv2)
Platform: Linux
Classifier: Development Status :: 4 - Beta
Classifier: Intended Audience :: Developers
Classifier: License :: OSI Approved :: GNU General Public License v2 (GPLv2)
Classifier: Natural Language :: English
Classifier: Operating System :: POSIX :: Linux
Classifier: Programming Language :: Python
Classifier: Programming Language :: Python :: 2.7
Classifier: Topic :: System :: Monitoring
